3rd-party.txt
LICENSE
MANIFEST.in
NOTICE
README.md
pyproject.toml
requirements-core.txt
requirements-default.txt
setup.py
datumaro/__init__.py
datumaro/__main__.py
datumaro/errors.py
datumaro/ops.py
datumaro/project.py
datumaro/version.py
datumaro/capi/pybind.cpp
datumaro/cli/__init__.py
datumaro/cli/__main__.py
datumaro/cli/commands/__init__.py
datumaro/cli/commands/convert.py
datumaro/cli/commands/detect_format.py
datumaro/cli/commands/diff.py
datumaro/cli/commands/download.py
datumaro/cli/commands/explain.py
datumaro/cli/commands/explore.py
datumaro/cli/commands/filter.py
datumaro/cli/commands/generate.py
datumaro/cli/commands/info.py
datumaro/cli/commands/merge.py
datumaro/cli/commands/patch.py
datumaro/cli/commands/stats.py
datumaro/cli/commands/transform.py
datumaro/cli/commands/validate.py
datumaro/cli/commands/require_project/__init__.py
datumaro/cli/commands/require_project/modification/__init__.py
datumaro/cli/commands/require_project/modification/add.py
datumaro/cli/commands/require_project/modification/create.py
datumaro/cli/commands/require_project/modification/export.py
datumaro/cli/commands/require_project/modification/import_.py
datumaro/cli/commands/require_project/modification/remove.py
datumaro/cli/commands/require_project/versioning/__init__.py
datumaro/cli/commands/require_project/versioning/checkout.py
datumaro/cli/commands/require_project/versioning/commit.py
datumaro/cli/commands/require_project/versioning/info.py
datumaro/cli/commands/require_project/versioning/log.py
datumaro/cli/commands/require_project/versioning/status.py
datumaro/cli/contexts/__init__.py
datumaro/cli/contexts/model.py
datumaro/cli/contexts/source.py
datumaro/cli/contexts/util.py
datumaro/cli/contexts/project/__init__.py
datumaro/cli/util/__init__.py
datumaro/cli/util/diff.py
datumaro/cli/util/errors.py
datumaro/cli/util/project.py
datumaro/components/__init__.py
datumaro/components/annotation.py
datumaro/components/cli_plugin.py
datumaro/components/config.py
datumaro_headless.egg-info/PKG-INFO
datumaro_headless.egg-info/SOURCES.txt
datumaro_headless.egg-info/dependency_links.txt
datumaro_headless.egg-info/entry_points.txt
datumaro_headless.egg-info/requires.txt
datumaro_headless.egg-info/top_level.txt