Metadata-Version: 2.1
Name: datumaro-headless
Version: 1.2.1.dev1684958806
Summary: Dataset Management Framework (Datumaro)
Home-page: https://github.com/openvinotoolkit/datumaro
Author: Intel
Author-email: emily.chun@intel.com
Classifier: Programming Language :: Python :: 3
Classifier: License :: OSI Approved :: MIT License
Classifier: Operating System :: OS Independent
Requires-Python: >=3.7
Provides-Extra: tf
Provides-Extra: tfds
Provides-Extra: tfds-dev
Provides-Extra: tf-gpu
Provides-Extra: default
License-File: LICENSE
License-File: NOTICE
